{
  "Routes": [
    {
      "DownstreamPathTemplate": "/api/restaurant/products",
      "DownstreamScheme": "https",
      "DownstreamHostAndPorts": [
        {
          "Host": "localhost",
          "Port": 7212
        }
      ],
      "UpstreamPathTemplate": "/products",
      "UpstreamHttpMethod": [ "Get" ]
    },
    {
      "DownstreamPathTemplate": "/api/restaurant/registerProduct",
      "DownstreamScheme": "https",
      "DownstreamHostAndPorts": [
        {
          "Host": "localhost",
          "Port": 7212
        }
      ],
      "UpstreamPathTemplate": "/register",
      "UpstreamHttpMethod": [ "Post" ]
    },
    {
      "DownstreamPathTemplate": "/api/order/order",
      "DownstreamScheme": "https",
      "DownstreamHostAndPorts": [
        {
          "Host": "localhost",
          "Port": 7212
        }
      ],
      "UpstreamPathTemplate": "/order",
      "UpstreamHttpMethod": [ "Post" ]
    },
    {
      "DownstreamPathTemplate": "/api/order/orders",
      "DownstreamScheme": "https",
      "DownstreamHostAndPorts": [
        {
          "Host": "localhost",
          "Port": 7212
        }
      ],
      "UpstreamPathTemplate": "/orders",
      "UpstreamHttpMethod": [ "Get" ]
    },
    {
      "DownstreamPathTemplate": "/api/order/accept",
      "DownstreamScheme": "https",
      "DownstreamHostAndPorts": [
        {
          "Host": "localhost",
          "Port": 7212
        }
      ],
      "UpstreamPathTemplate": "/accept",
      "UpstreamHttpMethod": [ "Put" ]
    },
    {
      "DownstreamPathTemplate": "/api/order/checkOrderAmount/{deliverer}",
      "DownstreamScheme": "https",
      "DownstreamHostAndPorts": [
        {
          "Host": "localhost",
          "Port": 7212
        }
      ],
      "UpstreamPathTemplate": "/checkAmount/{deliverer}",
      "UpstreamHttpMethod": [ "Get" ]
    },
    {
      "DownstreamPathTemplate": "/api/order/confirm",
      "DownstreamScheme": "https",
      "DownstreamHostAndPorts": [
        {
          "Host": "localhost",
          "Port": 7212
        }
      ],
      "UpstreamPathTemplate": "/confirm",
      "UpstreamHttpMethod": [ "Put" ]
    },
    {
      "DownstreamPathTemplate": "/api/order/orderStatus/{orderId}",
      "DownstreamScheme": "https",
      "DownstreamHostAndPorts": [
        {
          "Host": "localhost",
          "Port": 7212
        }
      ],
      "UpstreamPathTemplate": "/orderStatus/{orderId}",
      "UpstreamHttpMethod": [ "Get" ]
    },
    {
      "DownstreamPathTemplate": "/api/order/activeOrder/{email}",
      "DownstreamScheme": "https",
      "DownstreamHostAndPorts": [
        {
          "Host": "localhost",
          "Port": 7212
        }
      ],
      "UpstreamPathTemplate": "/activeOrder/{email}",
      "UpstreamHttpMethod": [ "Get" ]
    },
    {
      "DownstreamPathTemplate": "/api/order/orderInDelivery/{email}",
      "DownstreamScheme": "https",
      "DownstreamHostAndPorts": [
        {
          "Host": "localhost",
          "Port": 7212
        }
      ],
      "UpstreamPathTemplate": "/orderInDelivery/{email}",
      "UpstreamHttpMethod": [ "Get" ]
    },
    {
      "DownstreamPathTemplate": "/api/order/orderDelivered/{orderId}",
      "DownstreamScheme": "https",
      "DownstreamHostAndPorts": [
        {
          "Host": "localhost",
          "Port": 7212
        }
      ],
      "UpstreamPathTemplate": "/orderDelivered/{orderId}",
      "UpstreamHttpMethod": [ "Get" ]
    },
    {
      "DownstreamPathTemplate": "/api/order/finishedOrders/{email}",
      "DownstreamScheme": "https",
      "DownstreamHostAndPorts": [
        {
          "Host": "localhost",
          "Port": 7212
        }
      ],
      "UpstreamPathTemplate": "/finishedOrders/{email}",
      "UpstreamHttpMethod": [ "Get" ]
    },
    {
      "DownstreamPathTemplate": "/api/order/allOrders",
      "DownstreamScheme": "https",
      "DownstreamHostAndPorts": [
        {
          "Host": "localhost",
          "Port": 7212
        }
      ],
      "UpstreamPathTemplate": "/allOrders",
      "UpstreamHttpMethod": [ "Get" ]
    },
    {
      "DownstreamPathTemplate": "/api/order/delivererOrders/{email}",
      "DownstreamScheme": "https",
      "DownstreamHostAndPorts": [
        {
          "Host": "localhost",
          "Port": 7212
        }
      ],
      "UpstreamPathTemplate": "/delivererOrders/{email}",
      "UpstreamHttpMethod": [ "Get" ]
    },
    {
      "DownstreamPathTemplate": "/api/verification/register",
      "DownstreamScheme": "https",
      "DownstreamHostAndPorts": [
        {
          "Host": "localhost",
          "Port": 7007
        }
      ],
      "UpstreamPathTemplate": "/registerUser",
      "UpstreamHttpMethod": [ "Post" ]
    },
    {
      "DownstreamPathTemplate": "/api/verification/login",
      "DownstreamScheme": "https",
      "DownstreamHostAndPorts": [
        {
          "Host": "localhost",
          "Port": 7007
        }
      ],
      "UpstreamPathTemplate": "/loginUser",
      "UpstreamHttpMethod": [ "Post" ]
    },
    {
      "DownstreamPathTemplate": "/api/verification/facebookRegister",
      "DownstreamScheme": "https",
      "DownstreamHostAndPorts": [
        {
          "Host": "localhost",
          "Port": 7007
        }
      ],
      "UpstreamPathTemplate": "/facebookLogin",
      "UpstreamHttpMethod": [ "Post" ]
    },
    {
      "DownstreamPathTemplate": "/api/user/find/{email}",
      "DownstreamScheme": "https",
      "DownstreamHostAndPorts": [
        {
          "Host": "localhost",
          "Port": 7007
        }
      ],
      "UpstreamPathTemplate": "/user/{email}",
      "UpstreamHttpMethod": [ "Get" ]
    },
    {
      "DownstreamPathTemplate": "/api/user/changeName",
      "DownstreamScheme": "https",
      "DownstreamHostAndPorts": [
        {
          "Host": "localhost",
          "Port": 7007
        }
      ],
      "UpstreamPathTemplate": "/changeName",
      "UpstreamHttpMethod": [ "Put" ]
    },
    {
      "DownstreamPathTemplate": "/api/user/changeUsername",
      "DownstreamScheme": "https",
      "DownstreamHostAndPorts": [
        {
          "Host": "localhost",
          "Port": 7007
        }
      ],
      "UpstreamPathTemplate": "/changeUsername",
      "UpstreamHttpMethod": [ "Put" ]
    },
    {
      "DownstreamPathTemplate": "/api/user/addUsername",
      "DownstreamScheme": "https",
      "DownstreamHostAndPorts": [
        {
          "Host": "localhost",
          "Port": 7007
        }
      ],
      "UpstreamPathTemplate": "/addUsername",
      "UpstreamHttpMethod": [ "Post" ]
    },
    {
      "DownstreamPathTemplate": "/api/user/changeLastname",
      "DownstreamScheme": "https",
      "DownstreamHostAndPorts": [
        {
          "Host": "localhost",
          "Port": 7007
        }
      ],
      "UpstreamPathTemplate": "/changeLastname",
      "UpstreamHttpMethod": [ "Put" ]
    },
    {
      "DownstreamPathTemplate": "/api/user/changeAddress",
      "DownstreamScheme": "https",
      "DownstreamHostAndPorts": [
        {
          "Host": "localhost",
          "Port": 7007
        }
      ],
      "UpstreamPathTemplate": "/changeAddress",
      "UpstreamHttpMethod": [ "Put" ]
    },
    {
      "DownstreamPathTemplate": "/api/user/changeDate",
      "DownstreamScheme": "https",
      "DownstreamHostAndPorts": [
        {
          "Host": "localhost",
          "Port": 7007
        }
      ],
      "UpstreamPathTemplate": "/changeDate",
      "UpstreamHttpMethod": [ "Put" ]
    },
    {
      "DownstreamPathTemplate": "/api/user/changePassword",
      "DownstreamScheme": "https",
      "DownstreamHostAndPorts": [
        {
          "Host": "localhost",
          "Port": 7007
        }
      ],
      "UpstreamPathTemplate": "/changePassword",
      "UpstreamHttpMethod": [ "Put" ]
    },
    {
      "DownstreamPathTemplate": "/api/user/addDate",
      "DownstreamScheme": "https",
      "DownstreamHostAndPorts": [
        {
          "Host": "localhost",
          "Port": 7007
        }
      ],
      "UpstreamPathTemplate": "/addDate",
      "UpstreamHttpMethod": [ "Post" ]
    },
    {
      "DownstreamPathTemplate": "/api/user/addAddress",
      "DownstreamScheme": "https",
      "DownstreamHostAndPorts": [
        {
          "Host": "localhost",
          "Port": 7007
        }
      ],
      "UpstreamPathTemplate": "/addAddress",
      "UpstreamHttpMethod": [ "Post" ]
    },
    {
      "DownstreamPathTemplate": "/api/user/deliverers",
      "DownstreamScheme": "https",
      "DownstreamHostAndPorts": [
        {
          "Host": "localhost",
          "Port": 7007
        }
      ],
      "UpstreamPathTemplate": "/deliverers",
      "UpstreamHttpMethod": [ "Get" ]
    },
    {
      "DownstreamPathTemplate": "/api/user/verify",
      "DownstreamScheme": "https",
      "DownstreamHostAndPorts": [
        {
          "Host": "localhost",
          "Port": 7007
        }
      ],
      "UpstreamPathTemplate": "/verify",
      "UpstreamHttpMethod": [ "Put" ]
    },
    {
      "DownstreamPathTemplate": "/api/user/reject",
      "DownstreamScheme": "https",
      "DownstreamHostAndPorts": [
        {
          "Host": "localhost",
          "Port": 7007
        }
      ],
      "UpstreamPathTemplate": "/reject",
      "UpstreamHttpMethod": [ "Put" ]
    },
    {
      "DownstreamPathTemplate": "/api/user/addPhoto",
      "DownstreamScheme": "https",
      "DownstreamHostAndPorts": [
        {
          "Host": "localhost",
          "Port": 7007
        }
      ],
      "UpstreamPathTemplate": "/addPhoto",
      "UpstreamHttpMethod": [ "Post" ]
    }
  ],
  "GlobalConfiguration": {
  }
}